nucypher_snaptime-0.2.5.dist-info/licenses/LICENSE.txt
snaptime/__init__.py
snaptime/main.py
nucypher_snaptime-0.2.5.dist-info/METADATA
nucypher_snaptime-0.2.5.dist-info/WHEEL
nucypher_snaptime-0.2.5.dist-info/top_level.txt
nucypher_snaptime-0.2.5.dist-info/RECORD
